odoo/addons/ssi_loan/README.rst
odoo/addons/ssi_loan/__init__.py
odoo/addons/ssi_loan/__manifest__.py
odoo/addons/ssi_loan/menu.xml
odoo/addons/ssi_loan/data/approval_template_data.xml
odoo/addons/ssi_loan/data/base_automation_data.xml
odoo/addons/ssi_loan/data/ir_actions_server_data.xml
odoo/addons/ssi_loan/data/ir_sequence_data.xml
odoo/addons/ssi_loan/data/policy_template_data.xml
odoo/addons/ssi_loan/data/sequence_template_data.xml
odoo/addons/ssi_loan/demo/account_account_demo.xml
odoo/addons/ssi_loan/demo/account_journal_demo.xml
odoo/addons/ssi_loan/demo/loan_type_demo.xml
odoo/addons/ssi_loan/models/__init__.py
odoo/addons/ssi_loan/models/loan_additional_item.py
odoo/addons/ssi_loan/models/loan_collateral_in.py
odoo/addons/ssi_loan/models/loan_collateral_mixin.py
odoo/addons/ssi_loan/models/loan_collateral_out.py
odoo/addons/ssi_loan/models/loan_collateral_type.py
odoo/addons/ssi_loan/models/loan_in.py
odoo/addons/ssi_loan/models/loan_mixin.py
odoo/addons/ssi_loan/models/loan_out.py
odoo/addons/ssi_loan/models/loan_payment_schedule_additional_item_mixin.py
odoo/addons/ssi_loan/models/loan_payment_schedule_in.py
odoo/addons/ssi_loan/models/loan_payment_schedule_in_additional_item.py
odoo/addons/ssi_loan/models/loan_payment_schedule_mixin.py
odoo/addons/ssi_loan/models/loan_payment_schedule_out.py
odoo/addons/ssi_loan/models/loan_payment_schedule_out_additional_item.py
odoo/addons/ssi_loan/models/loan_type.py
odoo/addons/ssi_loan/models/res_company.py
odoo/addons/ssi_loan/models/res_config_settings.py
odoo/addons/ssi_loan/security/ir.model.access.csv
odoo/addons/ssi_loan/security/ir_module_category_data.xml
odoo/addons/ssi_loan/security/ir_rule_data.xml
odoo/addons/ssi_loan/security/res_group_data.xml
odoo/addons/ssi_loan/static/description/icon.png
odoo/addons/ssi_loan/views/loan_additional_item_views.xml
odoo/addons/ssi_loan/views/loan_collateral_type_views.xml
odoo/addons/ssi_loan/views/loan_in_views.xml
odoo/addons/ssi_loan/views/loan_mixin_views.xml
odoo14_addon_ssi_loan-14.0.1.8.0.dist-info/METADATA
odoo14_addon_ssi_loan-14.0.1.8.0.dist-info/WHEEL
odoo14_addon_ssi_loan-14.0.1.8.0.dist-info/top_level.txt
odoo14_addon_ssi_loan-14.0.1.8.0.dist-info/RECORD
